qualtrics/__init__.py
qualtrics/__main__.py
qualtrics/qualtrics_api.py
qualtrics_api-1.0.5.dist-info/METADATA
qualtrics_api-1.0.5.dist-info/RECORD
qualtrics_api-1.0.5.dist-info/WHEEL
qualtrics_api-1.0.5.dist-info/entry_points.txt
qualtrics_api-1.0.5.dist-info/top_level.txt
